seqtolang/__init__.py
seqtolang/detector.py
seqtolang/model.py
seqtolang/vectorizer.py
seqtolang/checkpoints/default_label2id.json
seqtolang/checkpoints/default_model.state_dict
seqtolang/checkpoints/default_vectorizer.pickle
seqtolang-0.1.4.dist-info/METADATA
seqtolang-0.1.4.dist-info/WHEEL
seqtolang-0.1.4.dist-info/top_level.txt
seqtolang-0.1.4.dist-info/RECORD
