Metadata-Version: 2.1
Name: seqtolang
Version: 0.1.4
Summary: Multi Langauge Documents Langauge identification
Home-page: https://github.com/hiredscorelabs/seqtolang
License: Apache
Keywords: Deep Learning Natural Language Processing NLP Machine Learning
Platform: UNKNOWN
Requires-Dist: torch (>=1.1.0)
